{
    "conf": [
        91,
        82,
        95,
        95,
        96,
        90,
        80,
        95,
        91,
        91,
        90,
        80,
        93,
        92,
        94,
        96,
        96,
        95,
        95,
        96,
        95,
        96,
        90,
        87,
        87,
        91,
        89,
        82,
        85,
        0,
        89,
        89,
        91,
        96,
        93,
        91,
        93,
        88,
        48,
        44
    ],
    "text": [
        "AMAZON.COM",
        "SERVICES",
        "LLC",
        "INPUT(ENTRADA):",
        "100-240V",
        "0.5A",
        "50/60H",
        "OUTPUT",
        "(SALIDA):",
        "12.0V1.25A",
        "O-C-",
        "ATTENTION-PRODUIT",
        "A",
        "COMMANDE",
        "ELECTRIQUE",
        "CAUTION-ELECTRICALLY",
        "OPERATED",
        "PRODUCT",
        "ACADAPTER",
        "EFICIENCIA",
        "ENERGETICA",
        "CUMPLE",
        "CON",
        "LANOM-029-ENER-2017",
        "MADE",
        "IN",
        "CHINA",
        "MODEL",
        ")",
        "NO.",
        "PA23NA",
        "CAN",
        "ICES(B)/NMB(B)",
        "PPGGCCLYYWW00KR"
    ],
    "total_conf": 3457,
    "average_conf": 86.425,
    "text_num": 40,
    "meth": "non"
}